tests/__init__.py
tests/test_main.py
win32path/__init__.py
win32path/win32path.py
win32path-0.1.0.dist-info/LICENSE
win32path-0.1.0.dist-info/METADATA
win32path-0.1.0.dist-info/WHEEL
win32path-0.1.0.dist-info/top_level.txt
win32path-0.1.0.dist-info/RECORD
