Metadata-Version: 2.1
Name: win32path
Version: 0.1.0
Summary: Easy to use and can be imported and used in any Python project.
Author: Emericdefay
License: MIT
License-File: LICENSE
